LICENSE
README.md
findmylibc/FindMyLibc.py
findmylibc/__init__.py
findmylibc-1.1.0.dist-info/METADATA
findmylibc-1.1.0.dist-info/WHEEL
findmylibc-1.1.0.dist-info/licenses/LICENSE
findmylibc-1.1.0.dist-info/RECORD
